pyrrhic/__init__.py
pyrrhic/commands.py
pyrrhic/hash.py
pyrrhic/rules.py
pyrrhic/scanners.py
pyrrhic/types.py
pyrrhic/util.py
pyrrhic-0.1b2.dist-info/COPYING.md
pyrrhic-0.1b2.dist-info/METADATA
pyrrhic-0.1b2.dist-info/WHEEL
pyrrhic-0.1b2.dist-info/top_level.txt
pyrrhic-0.1b2.dist-info/zip-safe
pyrrhic-0.1b2.dist-info/RECORD
